blindai/Intel_SGX_Provisioning_Certification_RootCA.pem
blindai/__init__.py
blindai/_dcap_attestation.py
blindai/_preprocess_audio.py
blindai/api.py
blindai/audio.py
blindai/client.py
blindai/core.py
blindai/manifest.toml
blindai/testing.py
blindai/utils.py
blindai-0.6.3.dist-info/METADATA
blindai-0.6.3.dist-info/WHEEL
blindai-0.6.3.dist-info/RECORD
