Metadata-Version: 2.1
Name: blindai
Version: 0.6.3
Summary: BlindAI Core / API is an open-source and easy-to-use Python library allowing you to query AI models with assurances that your private data will remain private
Home-page: https://github.com/mithril-security/blindai
Author: Mithril Security
Author-email: contact@mithrilsecurity.io
Requires-Python: >=3.8,<4.0
Classifier: Programming Language :: Python :: 3
Classifier: Programming Language :: Python :: 3.8
Classifier: Programming Language :: Python :: 3.9
Classifier: Programming Language :: Python :: 3.10
Classifier: Programming Language :: Python :: 3.11
Provides-Extra: torch
Requires-Dist: cbor2 (>=5.4.3,<6.0.0)
Requires-Dist: cryptography (>=39.0.1,<40.0.0)
Requires-Dist: ffmpeg-python (>=0.2.0,<0.3.0)
Requires-Dist: importlib-metadata (>=6.0.0,<7.0.0)
Requires-Dist: numpy (>=1.23.5,<1.24)
Requires-Dist: openai-whisper (>=20230308,<20230309)
Requires-Dist: requests (>=2.28.2,<3.0.0)
Requires-Dist: sgx-dcap-quote-verify-python (>=0.0.3,<0.0.4)
Requires-Dist: toml (>=0.10.2,<0.11.0)
Requires-Dist: torch (>=1.13.1,<2.0.0) ; extra == "torch"
Requires-Dist: torchaudio (==0.13.1)
Requires-Dist: transformers (==4.26.1)
Requires-Dist: typing-extensions (>=4.5.0,<5.0.0)
Project-URL: Documentation, https://blindai.mithrilsecurity.io
Project-URL: Repository, https://github.com/mithril-security/blindai
